scholarly_publications/__init__.py
scholarly_publications/cli.py
scholarly_publications/fetcher.py
scholarly_publications-0.6.dist-info/LICENSE
scholarly_publications-0.6.dist-info/METADATA
scholarly_publications-0.6.dist-info/WHEEL
scholarly_publications-0.6.dist-info/entry_points.txt
scholarly_publications-0.6.dist-info/top_level.txt
scholarly_publications-0.6.dist-info/RECORD
