Metadata-Version: 2.1
Name: scholarly_publications
Version: 0.6
Summary: A tool to fetch scholarly publications from Google Scholar by author ID
Home-page: https://github.com/ezefranca/scholarly_publications
Author: Ezequiel França
Author-email: ezequiel.franca@gmail.com
Project-URL: Bug Reports, https://github.com/ezefranca/scholarly_publications/issues
Project-URL: Source, https://github.com/ezefranca/scholarly_publications
Keywords: scholarly publications google scholar fetcher academia
Classifier: Development Status :: 4 - Beta
Classifier: Intended Audience :: Education
Classifier: Intended Audience :: Science/Research
Classifier: Topic :: Software Development :: Libraries :: Python Modules
Classifier: License :: OSI Approved :: MIT License
Classifier: Programming Language :: Python :: 3
Classifier: Programming Language :: Python :: 3 :: Only
Classifier: Programming Language :: Python :: 3.6
Classifier: Programming Language :: Python :: 3.7
Classifier: Programming Language :: Python :: 3.8
Classifier: Programming Language :: Python :: 3.9
Classifier: Programming Language :: Python :: 3.10
License-File: LICENSE
Requires-Dist: requests
Requires-Dist: beautifulsoup4
